funclog/__init__.py
funclog/about.py
funclog/funclog.py
funclog-0.3.0.dist-info/DESCRIPTION.rst
funclog-0.3.0.dist-info/METADATA
funclog-0.3.0.dist-info/metadata.json
funclog-0.3.0.dist-info/RECORD
funclog-0.3.0.dist-info/top_level.txt
funclog-0.3.0.dist-info/WHEEL
