Metadata-Version: 2.0
Name: funclog
Version: 0.3.0
Summary: A Python function logger
Home-page: https://github.com/gchina/funclog
Author: Grant China
Author-email: tikiboy@fastmail.fm
License: MIT
Keywords: function logger decorator
Platform: UNKNOWN
Classifier: Development Status :: 4 - Beta
Classifier: Intended Audience :: Developers
Classifier: Topic :: Software Development :: Libraries :: Python Modules
Classifier: License :: OSI Approved :: MIT License
Classifier: Programming Language :: Python :: 2
Classifier: Programming Language :: Python :: 2.7
Classifier: Programming Language :: Python :: 3
Classifier: Programming Language :: Python :: 3.3
Classifier: Programming Language :: Python :: 3.4
Classifier: Programming Language :: Python :: 3.5
